Workbook
Name aporte: 'Calculadora de Dividendos'!$F$12:$F$12
Name aporte_mensal: 'Calculadora de Dividendos'!$E$28:$F$28
Name aportes: 'Calculadora de Dividendos'!$F$12:$F$12
Name dividendos_mensais: 'Calculadora de Dividendos'!$F$16:$F$16
Name patrimonio: 'Calculadora de Dividendos'!$F$15:$F$15
Name qtd_anos: 'Calculadora de Dividendos'!$F$13:$F$13
Name rendimento_carteira: 'Calculadora de Dividendos'!$F$8:$F$8
Name salario: 'Calculadora de Dividendos'!$F$7:$F$7
Name sugestao_investimento: 'Calculadora de Dividendos'!$F$9:$F$9
Name taxa_mensal: 'Calculadora de Dividendos'!$F$14:$F$14

Sheet Calculadora de Dividendos
D2: Calculadora de Dividendos
D3: FII - Fundos Imobiliários
E4: ~Amanda S.S.Cruz
D6: CONFIGURAÇÕES
D7: Salário | F7: 2000
D8: Rendimento da Carteira | F8: 0.01
D9: Sugestão de Investimento | F9: =F7*30% -> 600
D11: INVESTIMENTO MENSAL
D12: Quanto Investir por mês? | F12: 200
D13: Por quantos anos? | F13: 5
D14: Taxa de rendimento mensal? | F14: 0.01
D15: Patrimônio acumulado? | F15: =FV($F$14,5*12,200*-1) -> 16333.934
D16: Dividendos mensais? | F16: =F15*$F$8 -> 163.33934
D19: CENÁRIOS | F19: Dividendos
C20: 2 | D20: Quanto em 2 anos? | E20: =FV($F$14,$C20*12,$F$12*-1) -> 5394.693 | F20: =$E20*$F$14 -> 53.94693
C21: 5 | D21: Quanto em 5 anos? | E21: =FV($F$14,$C21*12,$F$12*-1) -> 16333.934 | F21: =$E21*$F$14 -> 163.33934
C22: 10 | D22: Quanto em 10 anos? | E22: =FV($F$14,$C22*12,$F$12*-1) -> 46007.738 | F22: =$E22*$F$14 -> 460.07738
C23: 20 | D23: Quanto em 20 anos? | E23: =FV($F$14,$C23*12,$F$12*-1) -> 197851.07 | F23: =$E23*$F$14 -> 1978.5107
C24: 30 | D24: Quanto em 30 anos? | E24: =FV($F$14,$C24*12,$F$12*-1) -> 698992.83 | F24: =F14*E24 -> 6989.9283
D27: Perfil | E27: Conservador
D28: Valor a ser Investido por mês | E28: =F12 -> 200
D30: TIPO DE FII | E30: Percentual sugerido | F30: Valores
D31: PAPEL | E31: =VLOOKUP($E$27&"-"&$D31,Base!A2:$D$20,4,FALSE) -> 0.3 | F31: =$E31*$E$28 -> 60
D32: TIJOLO | E32: =VLOOKUP($E$27&"-"&$D32,Base!A3:$D$20,4,FALSE) -> 0.5 | F32: =$E32*$E$28 -> 100
D33: HÍBRIDOS | E33: =VLOOKUP($E$27&"-"&$D33,Base!A4:$D$20,4,FALSE) -> 0.1 | F33: =$E33*$E$28 -> 20
D34: FOF's | E34: =VLOOKUP($E$27&"-"&$D34,Base!A5:$D$20,4,FALSE) -> 0.1 | F34: =$E34*$E$28 -> 20
D35: DESENVOLVIMENTO | E35: =VLOOKUP($E$27&"-"&$D35,Base!A6:$D$20,4,FALSE) -> 0 | F35: =$E35*$E$28 -> 0
D36: HOTELARIAS | E36: =VLOOKUP($E$27&"-"&$D36,Base!A7:$D$20,4,FALSE) -> 0 | F36: =$E36*$E$28 -> 0
F37: =SUM(F31:F36) -> 200

Sheet Base
A2: CHAVE | B2: PERFIL | C2: TIPO DE FII | D2: % | G2: CHAVE | H2: %
A3: =$B3&"-"&$C3 -> Conservador-PAPEL | B3: Conservador | C3: PAPEL | D3: 0.3 | G3: =$B3&"-"&$C3 -> Conservador-PAPEL | H3: =VLOOKUP(G3,$A:$D,4,FALSE) -> 0.3
A4: =$B4&"-"&$C4 -> Conservador-TIJOLO | B4: Conservador | C4: TIJOLO | D4: 0.5 | G4: =$B4&"-"&$C4 -> Conservador-TIJOLO | H4: =VLOOKUP(G4,$A:$D,4,FALSE) -> 0.5
A5: =$B5&"-"&$C5 -> Conservador-HÍBRIDOS | B5: Conservador | C5: HÍBRIDOS | D5: 0.1 | G5: =$B5&"-"&$C5 -> Conservador-HÍBRIDOS | H5: =VLOOKUP(G5,$A:$D,4,FALSE) -> 0.1
A6: =$B6&"-"&$C6 -> Conservador-FOF's | B6: Conservador | C6: FOF's | D6: 0.1 | G6: =$B6&"-"&$C6 -> Conservador-FOF's | H6: =VLOOKUP(G6,$A:$D,4,FALSE) -> 0.1
A7: =$B7&"-"&$C7 -> Conservador-DESENVOLVIMENTO | B7: Conservador | C7: DESENVOLVIMENTO | D7: 0 | G7: =$B7&"-"&$C7 -> Conservador-DESENVOLVIMENTO | H7: =VLOOKUP(G7,$A:$D,4,FALSE) -> 0
A8: =$B8&"-"&$C8 -> Conservador-HOTELARIAS | B8: Conservador | C8: HOTELARIAS | D8: 0 | G8: =$B8&"-"&$C8 -> Conservador-HOTELARIAS | H8: =VLOOKUP(G8,$A:$D,4,FALSE) -> 0
A9: =$B9&"-"&$C9 -> Moderado-PAPEL | B9: Moderado | C9: PAPEL | D9: 0.32 | G9: =$B9&"-"&$C9 -> Moderado-PAPEL | H9: =VLOOKUP(G9,$A:$D,4,FALSE) -> 0.32
A10: =$B10&"-"&$C10 -> Moderado-TIJOLO | B10: Moderado | C10: TIJOLO | D10: 0.35 | G10: =$B10&"-"&$C10 -> Moderado-TIJOLO | H10: =VLOOKUP(G10,$A:$D,4,FALSE) -> 0.35
A11: =$B11&"-"&$C11 -> Moderado-HÍBRIDOS | B11: Moderado | C11: HÍBRIDOS | D11: 0.08 | G11: =$B11&"-"&$C11 -> Moderado-HÍBRIDOS | H11: =VLOOKUP(G11,$A:$D,4,FALSE) -> 0.08
A12: =$B12&"-"&$C12 -> Moderado-FOF's | B12: Moderado | C12: FOF's | D12: 0.05 | G12: =$B12&"-"&$C12 -> Moderado-FOF's | H12: =VLOOKUP(G12,$A:$D,4,FALSE) -> 0.05
A13: =$B13&"-"&$C13 -> Moderado-DESENVOLVIMENTO | B13: Moderado | C13: DESENVOLVIMENTO | D13: 0.1 | G13: =$B13&"-"&$C13 -> Moderado-DESENVOLVIMENTO | H13: =VLOOKUP(G13,$A:$D,4,FALSE) -> 0.1
A14: =$B14&"-"&$C14 -> Moderado-HOTELARIAS | B14: Moderado | C14: HOTELARIAS | D14: 0.1 | G14: =$B14&"-"&$C14 -> Moderado-HOTELARIAS | H14: =VLOOKUP(G14,$A:$D,4,FALSE) -> 0.1
... A20: =$B20&"-"&$C20 -> Arrojado-HOTELARIAS | B20: Arrojado | C20: HOTELARIAS | D20: 0.1 | G20: =$B20&"-"&$C20 -> Arrojado-HOTELARIAS | H20: =VLOOKUP(G20,$A:$D,4,FALSE) -> 0.1
